README.md
setup.py
echo/__init__.py
echo/downloader.py
echo/main.py
echo360download.egg-info/PKG-INFO
echo360download.egg-info/SOURCES.txt
echo360download.egg-info/dependency_links.txt
echo360download.egg-info/entry_points.txt
echo360download.egg-info/requires.txt
echo360download.egg-info/top_level.txt