Metadata-Version: 2.1
Name: echo360download
Version: 1.0
Summary: Download Echo 360 files
Home-page: https://github.com/visgean/gimme-echo360
Author: Visgean
Author-email: visgean@gmail.com
License: MIT
Keywords: exif sql
Platform: UNKNOWN
Classifier: License :: OSI Approved :: MIT License
Classifier: Programming Language :: Python :: 3
Classifier: Programming Language :: Python :: 3.7
